semantic_search/__init__.py
semantic_search/__version__.py
semantic_search-0.0.0.dist-info/LICENSE
semantic_search-0.0.0.dist-info/METADATA
semantic_search-0.0.0.dist-info/WHEEL
semantic_search-0.0.0.dist-info/top_level.txt
semantic_search-0.0.0.dist-info/RECORD
